MANIFEST.in
README.txt
setup.cfg
setup.py
collective/__init__.py
collective.conference.egg-info/PKG-INFO
collective.conference.egg-info/SOURCES.txt
collective.conference.egg-info/dependency_links.txt
collective.conference.egg-info/entry_points.txt
collective.conference.egg-info/namespace_packages.txt
collective.conference.egg-info/not-zip-safe
collective.conference.egg-info/paster_plugins.txt
collective.conference.egg-info/requires.txt
collective.conference.egg-info/top_level.txt
collective/conference/INTEGRATION.txt
collective/conference/__init__.py
collective/conference/conference.py
collective/conference/configure.zcml
collective/conference/indexer.py
collective/conference/interfaces.py
collective/conference/participant.py
collective/conference/session.py
collective/conference/tests.py
collective/conference/vocabulary.py
collective/conference/browser/__init__.py
collective/conference/browser/agenda.py
collective/conference/browser/conference_view.py
collective/conference/browser/listings.py
collective/conference/browser/location.py
collective/conference/browser/macros.py
collective/conference/browser/participant_view.py
collective/conference/browser/propose.py
collective/conference/browser/register.py
collective/conference/browser/session_view.py
collective/conference/browser/templates/agenda.pt
collective/conference/browser/templates/attendance_list.pt
collective/conference/browser/templates/conference_view.pt
collective/conference/browser/templates/listing.pt
collective/conference/browser/templates/location.pt
collective/conference/browser/templates/macros.pt
collective/conference/browser/templates/participant_view.pt
collective/conference/browser/templates/session_view.pt
collective/conference/locales/README.txt
collective/conference/models/conference.xml
collective/conference/models/participant.xml
collective/conference/models/room.xml
collective/conference/models/session.xml
collective/conference/profiles/default/catalog.xml
collective/conference/profiles/default/metadata.xml
collective/conference/profiles/default/types.xml
collective/conference/profiles/default/workflows.xml
collective/conference/profiles/default/types/collective.conference.conference.xml
collective/conference/profiles/default/types/collective.conference.participant.xml
collective/conference/profiles/default/types/collective.conference.session.xml
