Metadata-Version: 1.0
Name: collective.conference
Version: 1.0a2
Summary: Conference management
Home-page: https://github.com/inigoconsulting/collective.conference
Author: Inigo Consulting
Author-email: info@inigo-tech.com
License: GPLv2+
Keywords: conference management plone zope
Platform: UNKNOWN
Classifier: Framework :: Plone
Classifier: Programming Language :: Python
Classifier: Topic :: Software Development :: Libraries :: Python Modules
